swarmauri_developer/DeveloperAssistant.py
swarmauri_developer/__init__.py
swarmauri_developer-0.0.9.dist-info/METADATA
swarmauri_developer-0.0.9.dist-info/WHEEL
swarmauri_developer-0.0.9.dist-info/entry_points.txt
swarmauri_developer-0.0.9.dist-info/top_level.txt
swarmauri_developer-0.0.9.dist-info/RECORD
